{
    "id": "40", 
    "records": [
        {
            "date": "2001-10-31", 
            "id": 313, 
            "note": "Winnie is a 6-year-old hispanic male diagnosed with cancer of the blood. He has heart problems. "
        }, 
        {
            "date": "2001-11-18", 
            "id": 314, 
            "note": "Winnie is a 6-year-old hispanic male diagnosed with Leukemia. Leukemia is cancer of the blood and bone marrow (the soft material in the center of most bones).He has had problems in school. "
        }, 
        {
            "date": "2001-11-27", 
            "id": 315, 
            "note": "Winnie is a 6-year-old Hispanic male diagnosed with leukemia. He has chronic heart failure. He reports suffering from major anxiety. Winnie reports sleeping at night is difficult.He has had problems in school. "
        }, 
        {
            "date": "2001-12-07", 
            "id": 316, 
            "note": "He has had problems in school. "
        }, 
        {
            "date": "2001-12-16", 
            "id": 317, 
            "note": "Winnie is a 6-year-old Hispanic male diagnosed with leukemia. He reports suffering from major anxiety. Winnie reports sleeping at night is difficult.He has had problems in school. "
        }, 
        {
            "date": "2001-12-19", 
            "id": 318, 
            "note": "Winnie is a 6-year-old Hispanic male diagnosed with leukemia. Leukemia is cancer of the blood and bone marrow (the soft material in the center of most bones).He reports suffering from major anxiety. Winnie reports sleeping at night is difficult."
        }, 
        {
            "date": "2001-12-27", 
            "id": 319, 
            "note": "He has chronic heart failure. He reports suffering from major anxiety. Winnie reports sleeping at night is difficult.He has had problems in school. "
        }, 
        {
            "date": "2002-01-11", 
            "id": 320, 
            "note": "He reports suffering from major anxiety. Winnie reports sleeping at night is difficult."
        }
    ]
}